continual_learning/__init__.py
continual_learning/backbone_networks/__init__.py
continual_learning/backbone_networks/alexnet.py
continual_learning/backbone_networks/lenet.py
continual_learning/backbone_networks/vgg.py
continual_learning/backbone_networks/resnet/__init__.py
continual_learning/backbone_networks/resnet/resnet.py
continual_learning/backbone_networks/resnet/torch_resnet.py
continual_learning/datasets/__init__.py
continual_learning/datasets/cifar.py
continual_learning/datasets/core50.py
continual_learning/datasets/mnist.py
continual_learning/datasets/svhn.py
continual_learning/datasets/tiny_imagenet.py
continual_learning/datasets/base/__init__.py
continual_learning/datasets/base/base.py
continual_learning/datasets/base/split_functions.py
continual_learning/datasets/base/utils.py
continual_learning/eval/__init__.py
continual_learning/eval/evalautor.py
continual_learning/eval/metrics/__init__.py
continual_learning/eval/metrics/base.py
continual_learning/eval/metrics/cl.py
continual_learning/eval/metrics/classification.py
continual_learning/eval/metrics/general.py
continual_learning/methods/__init__.py
continual_learning/methods/base.py
continual_learning/methods/class_incremental/__init__.py
continual_learning/methods/task_incremental/__init__.py
continual_learning/methods/task_incremental/multi_task/__init__.py
continual_learning/methods/task_incremental/multi_task/gg/__init__.py
continual_learning/methods/task_incremental/multi_task/gg/base.py
continual_learning/methods/task_incremental/multi_task/gg/batch_ensemble/BE.py
continual_learning/methods/task_incremental/multi_task/gg/batch_ensemble/__init__.py
continual_learning/methods/task_incremental/multi_task/gg/batch_ensemble/base.py
continual_learning/methods/task_incremental/multi_task/gg/er/ER.py
continual_learning/methods/task_incremental/multi_task/gg/er/__init__.py
continual_learning/methods/task_incremental/multi_task/gg/ewc/EWC.py
continual_learning-0.1.6.6.dist-info/LICENSE
continual_learning-0.1.6.6.dist-info/METADATA
continual_learning-0.1.6.6.dist-info/WHEEL
continual_learning-0.1.6.6.dist-info/top_level.txt
continual_learning-0.1.6.6.dist-info/RECORD
