Metadata-Version: 2.1
Name: continual-learning
Version: 0.1.6.6
Summary: A base CL framework to speed-up prototyping and testing
Home-page: https://github.com/jaryP/ContinualAI
Author: Jary Pomponi
Author-email: jarypomponi@gmail.org
License: UNKNOWN
Keywords: continual learning
Platform: UNKNOWN
Classifier: Intended Audience :: Science/Research
Classifier: Intended Audience :: Education
Classifier: Intended Audience :: Other Audience
Classifier: Programming Language :: Python :: 3
Classifier: License :: OSI Approved :: MIT License
Classifier: Operating System :: OS Independent
Classifier: Development Status :: 1 - Planning
Classifier: Topic :: Scientific/Engineering
Classifier: Topic :: Scientific/Engineering :: Artificial Intelligence
Classifier: Environment :: Console
Requires-Python: >=3.7
License-File: LICENSE
Requires-Dist: torch
Requires-Dist: torchvision
Requires-Dist: numpy
Requires-Dist: quadprog
Requires-Dist: scipy
